weather.py
zimy_demo_weather-0.1.2.dist-info/METADATA
zimy_demo_weather-0.1.2.dist-info/WHEEL
zimy_demo_weather-0.1.2.dist-info/entry_points.txt
zimy_demo_weather-0.1.2.dist-info/top_level.txt
zimy_demo_weather-0.1.2.dist-info/RECORD
