Metadata-Version: 2.4
Name: zimy-demo-weather
Version: 0.1.2
Summary: 输入地址查天气
Requires-Python: >=3.10
Requires-Dist: httpx>=0.28.1
Requires-Dist: mcp>=1.6.0
